ltree_models/__init__.py
ltree_models/database.py
ltree_models/models.py
ltree_models/populate.py
ltree_models-0.1.0.dist-info/METADATA
ltree_models-0.1.0.dist-info/WHEEL
ltree_models-0.1.0.dist-info/top_level.txt
ltree_models-0.1.0.dist-info/RECORD
