Metadata-Version: 2.1
Name: ltree-models
Version: 0.1.0
Summary: sqlalchemy models for ltree.
Home-page: UNKNOWN
Author: Colin Higgs
Author-email: colin.higgs70@gmail.com
License: GNU Affero General Public License v3 or later (AGPLv3+)
Keywords: json,api,json-api,jsonapi,jsonschema,openapi,pyramid,sqlalchemy
Platform: UNKNOWN
Classifier: Development Status :: 5 - Production/Stable
Classifier: Intended Audience :: Developers
Classifier: License :: OSI Approved :: GNU Affero General Public License v3 or later (AGPLv3+)
Classifier: Programming Language :: Python :: 3
Requires-Dist: SQLAlchemy (>=1.4)
Requires-Dist: sqlalchemy-utils
Provides-Extra: testing
Requires-Dist: psycopg2 ; extra == 'testing'
Requires-Dist: testing.postgresql ; extra == 'testing'
Requires-Dist: tox ; extra == 'testing'
